mtots/__init__.py
mtots/module_finder.py
mtots/test.py
mtots/parser/__init__.py
mtots/parser/base.py
mtots/parser/combinator.py
mtots/text/__init__.py
mtots/text/barley/__init__.py
mtots/text/barley/ast.py
mtots/text/barley/lexer.py
mtots/text/barley/parser.py
mtots/text/java/__init__.py
mtots/text/java/ast.py
mtots/text/java/lexer.py
mtots/text/nc/__init__.py
mtots/text/nc/__main__.py
mtots/text/nc/ast.py
mtots/text/nc/cst.py
mtots/text/nc/cxx.py
mtots/text/nc/errors.py
mtots/text/nc/lexer.py
mtots/text/nc/parser.py
mtots/text/nc/resolver.py
mtots/text/nc/scopes.py
mtots/tp/__init__.py
mtots/tp/dataclasses/__init__.py
mtots/tp/dataclasses/main.py
mtots/usaco/__init__.py
mtots/usaco/_template.py
mtots/usaco/barn1.py
mtots/usaco/combo.py
mtots/usaco/crypt1.py
mtots/usaco/dualpal.py
mtots/usaco/milk.py
mtots/util/__init__.py
mtots/util/dataclasses.py
mtots/util/iifes.py
mtots/util/memoizer.py
mtots/util/multimethods.py
mtots/util/scopes.py
mtots/util/typing.py
mtots-0.0.3.dist-info/LICENSE
mtots-0.0.3.dist-info/METADATA
mtots-0.0.3.dist-info/WHEEL
mtots-0.0.3.dist-info/top_level.txt
mtots-0.0.3.dist-info/RECORD
