Metadata-Version: 2.1
Name: mtots
Version: 0.0.3
Summary: a collection of utilities
Home-page: https://github.com/math4tots/mtots
Author: math4tots
Author-email: math4tots@gmail.com
License: UNKNOWN
Platform: UNKNOWN
